denmonitor
