Metadata-Version: 1.1
Name: DEnM-Visualizer
Version: 1.0.2
Summary: TriKinetics Environnemental Monitor visualiser
Home-page: https://github.com/samrund/DEnM_Visualizer
Author: Marek Strelec
Author-email: marek.strelec@gmail.com
License: MIT
Keywords: TriKinetics Monitor visualiser
Platform: UNKNOWN
Classifier: Development Status :: 5 - Production/Stable
Classifier: Intended Audience :: Science/Research
Classifier: Topic :: Scientific/Engineering :: Bio-Informatics
Classifier: License :: OSI Approved :: MIT License
Classifier: Programming Language :: Python :: 2
Classifier: Programming Language :: Python :: 2.7
Classifier: Operating System :: MacOS :: MacOS X
Classifier: Operating System :: Microsoft :: Windows
